{
 "id": 2,
 "name": "generated",
 "bounds": [
  720,
  1000
 ],
 "plates": [
  {
   "id": 0,
   "layer": 0,
   "color": "#a2b1bf",
   "points": [
    [
     140,
     238
    ],
    [
     176,
     198
    ],
    [
     195,
     198
    ],
    [
     298,
     217
    ],
    [
     291,
     372
    ],
    [
     260,
     402
    ],
    [
     221,
     407
    ],
    [
     158,
     340
    ]
   ],
   "screws": [
    [
     266,
     266
    ],
    [
     193,
     244
    ]
   ]
  },
  {
   "id": 1,
   "layer": 0,
   "color": "#a2b1bf",
   "points": [
    [
     366,
     739
    ],
    [
     586,
     739
    ],
    [
     586,
     843
    ],
    [
     366,
     843
    ]
   ],
   "screws": [
    [
     493,
     780
    ]
   ]
  },
  {
   "id": 2,
   "layer": 1,
   "color": "#8a9db1",
   "points": [
    [
     453,
     879
    ],
    [
     453,
     727
    ],
    [
     572,
     731
    ],
    [
     566,
     831
    ],
    [
     537,
     871
    ]
   ],
   "screws": [
    [
     490,
     794
    ],
    [
     526,
     838
    ]
   ]
  }
 ]
}
