{
 "id": 29,
 "name": "generated",
 "bounds": [
  720,
  1000
 ],
 "plates": [
  {
   "id": 0,
   "layer": 0,
   "color": "#98a8b8",
   "points": [
    [
     287,
     771
    ],
    [
     318,
     753
    ],
    [
     386,
     737
    ],
    [
     440,
     781
    ],
    [
     416,
     792
    ],
    [
     321,
     820
    ]
   ],
   "screws": [
    [
     357,
     777
    ]
   ]
  },
  {
   "id": 1,
   "layer": 0,
   "color": "#a2b1bf",
   "points": [
    [
     341,
     313
    ],
    [
     402,
     340
    ],
    [
     440,
     467
    ],
    [
     455,
     523
    ],
    [
     453,
     542
    ],
    [
     350,
     533
    ]
   ],
   "screws": [
    [
     374,
     399
    ]
   ]
  },
  {
   "id": 2,
   "layer": 0,
   "color": "#8f9fae",
   "points": [
    [
     120,
     325
    ],
    [
     327,
     325
    ],
    [
     327,
     462
    ],
    [
     120,
     462
    ]
   ],
   "screws": [
    [
     299,
     387
    ]
   ]
  },
  {
   "id": 3,
   "layer": 1,
   "color": "#8a9db1",
   "points": [
    [
     282,
     756
    ],
    [
     431,
     726
    ],
    [
     459,
     868
    ],
    [
     311,
     898
    ]
   ],
   "screws": [
    [
     411,
     839
    ],
    [
     372,
     786
    ],
    [
     351,
     853
    ]
   ]
  },
  {
   "id": 4,
   "layer": 1,
   "color": "#8a9db1",
   "points": [
    [
     244,
     334
    ],
    [
     328,
     325
    ],
    [
     381,
     324
    ],
    [
     388,
     407
    ],
    [
     365,
     477
    ],
    [
     285,
     488
    ],
    [
     245,
     418
    ]
   ],
   "screws": [
    [
     303,
     455
    ]
   ]
  },
  {
   "id": 5,
   "layer": 2,
   "color": "#b1bec9",
   "points": [
    [
     202,
     397
    ],
    [
     223,
     257
    ],
    [
     375,
     321
    ],
    [
     385,
     393
    ],
    [
     239,
     477
    ]
   ],
   "screws": [
    [
     268,
     389
    ],
    [
     277,
     319
    ]
   ]
  },
  {
   "id": 6,
   "layer": 3,
   "color": "#ccb793",
   "points": [
    [
     181,
     325
    ],
    [
     331,
     325
    ],
    [
     331,
     414
    ],
    [
     181,
     414
    ]
   ],
   "screws": [
    [
     298,
     381
    ],
    [
     236,
     370
    ]
   ]
  }
 ]
}
