{
 "version": 2,
 "id": 26,
 "name": "Flamingo II",
 "silhouette": "flamingo",
 "bounds": [
  720,
  1000
 ],
 "board_holes": [
  [
   321.8,
   575.7
  ],
  [
   385.8,
   553.4
  ],
  [
   185.7,
   237.1
  ],
  [
   461.2,
   522.7
  ],
  [
   120.0,
   70.0
  ],
  [
   280.0,
   70.0
  ],
  [
   440.0,
   70.0
  ],
  [
   600.0,
   70.0
  ],
  [
   362.9,
   652.7
  ]
 ],
 "plates": [
  {
   "id": 0,
   "layer": 0,
   "color": "#e08298",
   "points": [
    [
     191.2,
     192.7
    ],
    [
     252.6,
     208.3
    ],
    [
     268.0,
     254.7
    ],
    [
     214.4,
     262.3
    ],
    [
     253.3,
     362.7
    ],
    [
     314.9,
     455.6
    ],
    [
     558.5,
     652.3
    ],
    [
     466.6,
     697.8
    ],
    [
     498.0,
     898.6
    ],
    [
     559.6,
     914.2
    ],
    [
     559.7,
     937.3
    ],
    [
     452.0,
     937.1
    ],
    [
     451.3,
     713.1
    ],
    [
     176.2,
     285.2
    ],
    [
     129.9,
     254.2
    ],
    [
     129.8,
     207.9
    ]
   ],
   "holes": [
    [
     385.8,
     553.4
    ],
    [
     185.7,
     237.1
    ]
   ]
  },
  {
   "id": 1,
   "layer": 0,
   "color": "#f092a8",
   "points": [
    [
     408.9,
     485.4
    ],
    [
     527.6,
     500.9
    ],
    [
     589.1,
     560.3
    ],
    [
     559.4,
     651.4
    ],
    [
     316.3,
     454.1
    ]
   ],
   "holes": [
    [
     461.2,
     522.7
    ]
   ]
  },
  {
   "id": 2,
   "layer": 0,
   "color": "#d07288",
   "points": [
    [
     298.3,
     517.7
    ],
    [
     237.5,
     409.2
    ],
    [
     175.7,
     285.5
    ],
    [
     450.8,
     713.6
    ],
    [
     374.1,
     697.6
    ],
    [
     298.2,
     650.9
    ],
    [
     269.6,
     574.7
    ]
   ],
   "holes": [
    [
     321.8,
     575.7
    ],
    [
     362.9,
     652.7
    ]
   ]
  },
  {
   "id": 3,
   "layer": 1,
   "color": "#ffa2b8",
   "points": [
    [
     196.7,
     437.7
    ],
    [
     306.1,
     367.4
    ],
    [
     430.5,
     560.9
    ],
    [
     321.1,
     631.2
    ]
   ],
   "holes": [
    [
     321.8,
     575.7
    ],
    [
     385.8,
     553.4
    ]
   ]
  }
 ],
 "screws": [
  {
   "hole": 0,
   "plates": [
    2,
    3
   ]
  },
  {
   "hole": 1,
   "plates": [
    0,
    3
   ]
  },
  {
   "hole": 2,
   "plates": [
    0
   ]
  },
  {
   "hole": 3,
   "plates": [
    1
   ]
  }
 ]
}
